build/lib/cn2an/__init__.py
build/lib/cn2an/an2cn.py
build/lib/cn2an/an2cn_test.py
build/lib/cn2an/cn2an.py
build/lib/cn2an/cn2an_test.py
build/lib/cn2an/conf.py
build/lib/cn2an/performance.py
build/lib/cn2an/transform.py
build/lib/cn2an/transform_test.py
build/lib/cn2an/utils.py
cn2an/__init__.py
cn2an/an2cn.py
cn2an/an2cn_test.py
cn2an/cn2an.py
cn2an/cn2an_test.py
cn2an/conf.py
cn2an/config.yaml
cn2an/config.yml
cn2an/performance.py
cn2an/transform.py
cn2an/transform_test.py
cn2an/utils.py
example/an2cn_core.py
example/cn2an_core.py
src/cn2an-site-v0.3.11.png
src/cn2an-site-v0.4.1.png
src/cn2an-site.png
cn2an-0.5.22.dist-info/LICENSE
cn2an-0.5.22.dist-info/METADATA
cn2an-0.5.22.dist-info/WHEEL
cn2an-0.5.22.dist-info/top_level.txt
cn2an-0.5.22.dist-info/zip-safe
cn2an-0.5.22.dist-info/RECORD
