Metadata-Version: 2.1
Name: cn2an
Version: 0.5.22
Summary: Convert Chinese numerals and Arabic numerals.
Home-page: https://github.com/Ailln/cn2an
Author: Ailln
Author-email: kinggreenhall@gmail.com
License: MIT License
Classifier: Programming Language :: Python :: 3
Classifier: Programming Language :: Python :: 3.6
Classifier: Programming Language :: Python :: 3.7
Classifier: Programming Language :: Python :: 3.8
Classifier: License :: OSI Approved :: MIT License
Classifier: Operating System :: OS Independent
Requires-Python: >=3.6
License-File: LICENSE
